sole_bili_get/__init__.py
sole_bili_get/av2bv.py
sole_bili_get/bili_get.py
sole_bili_get/chrome_cookie.py
sole_bili_get/file_lock.py
sole_bili_get/utils.py
sole_bili_get-0.0.12.dist-info/LICENSE.txt
sole_bili_get-0.0.12.dist-info/METADATA
sole_bili_get-0.0.12.dist-info/WHEEL
sole_bili_get-0.0.12.dist-info/entry_points.txt
sole_bili_get-0.0.12.dist-info/top_level.txt
sole_bili_get-0.0.12.dist-info/RECORD
