Metadata-Version: 2.1
Name: sole_bili_get
Version: 0.0.12
Summary: A simple tool to download videos from bilibili{*≧∀≦}
Home-page: https://github.com/muggledy/bili-get
Author: muggledy
Author-email: zgjsycfndy2015@163.com
License: MIT
Classifier: License :: OSI Approved :: MIT License
Classifier: Operating System :: Microsoft :: Windows
Classifier: Operating System :: POSIX
Requires-Python: >=3.6
License-File: LICENSE.txt
Requires-Dist: requests
Requires-Dist: colorama
Requires-Dist: psutil
Requires-Dist: pycryptodome ; platform_system == "Windows"
Requires-Dist: pypiwin32 ; platform_system == "Windows"
